intasend/__init__.py
intasend/chargebacks.py
intasend/client.py
intasend/collections.py
intasend/customers.py
intasend/exceptions.py
intasend/payment_links.py
intasend/transfers.py
intasend/wallets.py
intasend_python-1.1.1.dist-info/LICENSE
intasend_python-1.1.1.dist-info/METADATA
intasend_python-1.1.1.dist-info/WHEEL
intasend_python-1.1.1.dist-info/top_level.txt
intasend_python-1.1.1.dist-info/RECORD
